{
  "config": {
    "abort": {
      "single_instance_allowed": "只允许添加一个 HA数据统一存储系统 条目"
    },
    "step": {
      "user": {
        "title": "HA数据统一存储系统",
        "description": "HA数据统一存储系统。添加后即可通过 API 动态管理监控实体和自定义路由，无需重启 Home Assistant。"
      }
    }
  },
  "options": {
    "step": {
      "init": {
        "title": "监控实体管理",
        "description": "{menu_info}",
        "menu_options": {
          "add_device": "添加设备类实体",
          "add_env": "添加传感器类实体",
          "remove": "删除实体",
          "view": "查看实体",
          "timezone": "时区设置",
          "log_retention": "日志保留时长",
          "route_menu": "路由管理",
          "bridge_menu": "设备桥接",
          "done": "完成"
        }
      },
      "add_device": {
        "title": "添加设备类实体",
        "description": "{hint}",
        "data": {
          "entity_ids": "输入实体 ID"
        }
      },
      "add_env": {
        "title": "添加传感器类实体",
        "description": "{hint}",
        "data": {
          "env_entries": "输入传感器配置"
        }
      },
      "remove": {
        "title": "删除监控实体",
        "description": "{hint}",
        "data": {
          "entity_ids": "输入要删除的实体 ID"
        }
      },
      "view": {
        "title": "查看监控实体",
        "description": "{info}"
      },
      "route_menu": {
        "title": "自定义路由管理",
        "description": "{routes_info}",
        "menu_options": {
          "route_add": "添加路由",
          "route_list": "查看路由",
          "route_delete": "删除路由",
          "route_back": "返回主菜单"
        }
      },
      "timezone": {
        "title": "时区设置",
        "description": "当前时区偏移: {current_tz} 小时\n\n请输入新的时区偏移值（相对于 UTC 的小时数，例如东八区为 8）。",
        "data": {
          "tz_offset": "时区偏移（小时）"
        }
      },
      "log_retention": {
        "title": "日志保留时长",
        "description": "当前日志保留 {current_days} 天。\n\n请选择本地日志文件的保留天数，超过该天数的日志将被自动删除。",
        "data": {
          "log_retention_days": "日志保留天数"
        }
      },
      "route_add": {
        "title": "添加自定义路由",
        "description": "{hint}",
        "data": {
          "route_path": "路由路径",
          "sql_statement": "SQL 语句",
          "description": "描述（选填）"
        }
      },
      "route_list": {
        "title": "查看自定义路由",
        "description": "{info}"
      },
      "route_delete": {
        "title": "删除自定义路由",
        "description": "{hint}",
        "data": {
          "route_path": "要删除的路由路径"
        }
      },
      "bridge_menu": {
        "title": "设备桥接管理",
        "description": "{bridge_info}",
        "menu_options": {
          "bridge_add_connection": "添加远程连接",
          "bridge_add_entity": "添加桥接实体",
          "bridge_view": "查看桥接配置",
          "bridge_delete": "删除桥接配置",
          "bridge_back": "返回主菜单"
        }
      },
      "bridge_add_connection": {
        "title": "添加远程连接",
        "description": "{hint}",
        "data": {
          "name": "连接名称（选填）",
          "remote_url": "远程 HA 地址",
          "access_token": "长期访问令牌",
          "verify_ssl": "验证 SSL 证书"
        }
      },
      "bridge_add_entity": {
        "title": "添加桥接实体",
        "description": "{hint}",
        "data": {
          "connection_id": "选择连接",
          "entity_ids": "实体 ID（每行一个）"
        }
      },
      "bridge_view": {
        "title": "查看桥接配置",
        "description": "{info}"
      },
      "bridge_delete": {
        "title": "删除桥接配置",
        "description": "{hint}",
        "data": {
          "delete_type": "删除类型",
          "target_id": "要删除的 ID"
        }
      },
      "bridge_back": {
        "title": "返回"
      },
      "done": {
        "title": "完成"
      }
    }
  },
  "entity": {
    "switch": {
      "api_access": {
        "name": "API 访问"
      },
      "db_viewer_access": {
        "name": "数据库浏览器"
      },
      "db_edit_access": {
        "name": "数据库修改"
      }
    },
    "sensor": {
      "monitored_entities": {
        "name": "监控实体列表"
      }
    }
  }
}
